ccpca/__init__.py
ccpca/ccpca.py
ccpca/performance_test.py
ccpca-0.2.4.dist-info/licenses/LICENSE
cpca/__init__.py
cpca/cpca.py
fc_view/__init__.py
fc_view/mat_reorder.py
fc_view/opt_sign_flip.py
ccpca-0.2.4.dist-info/METADATA
ccpca-0.2.4.dist-info/WHEEL
ccpca-0.2.4.dist-info/top_level.txt
ccpca-0.2.4.dist-info/RECORD
